MANIFEST.in
README.rst
setup.cfg
setup.py
collective/__init__.py
collective.z3cform.datagridfield_demo.egg-info/PKG-INFO
collective.z3cform.datagridfield_demo.egg-info/SOURCES.txt
collective.z3cform.datagridfield_demo.egg-info/dependency_links.txt
collective.z3cform.datagridfield_demo.egg-info/entry_points.txt
collective.z3cform.datagridfield_demo.egg-info/namespace_packages.txt
collective.z3cform.datagridfield_demo.egg-info/not-zip-safe
collective.z3cform.datagridfield_demo.egg-info/requires.txt
collective.z3cform.datagridfield_demo.egg-info/top_level.txt
collective/z3cform/__init__.py
collective/z3cform/datagridfield_demo/__init__.py
collective/z3cform/datagridfield_demo/configure.zcml
collective/z3cform/datagridfield_demo/browser/__init__.py
collective/z3cform/datagridfield_demo/browser/menu.py
collective/z3cform/datagridfield_demo/browser/simple.py
collective/z3cform/datagridfield_demo/browser/simple_object.py
collective/z3cform/datagridfield_demo/browser/menu_templates/menu.pt
collective/z3cform/datagridfield_demo/browser/simple_object_templates/editform.pt
collective/z3cform/datagridfield_demo/browser/simple_object_templates/editform2.pt
collective/z3cform/datagridfield_demo/browser/simple_object_templates/editform3.pt
collective/z3cform/datagridfield_demo/browser/simple_object_templates/editform4.pt
collective/z3cform/datagridfield_demo/browser/simple_object_templates/editform4b.pt
collective/z3cform/datagridfield_demo/browser/simple_object_templates/editform5.pt
collective/z3cform/datagridfield_demo/browser/simple_object_templates/editform6.pt
collective/z3cform/datagridfield_demo/browser/simple_object_templates/editform7.pt
collective/z3cform/datagridfield_demo/browser/simple_object_templates/editform8.pt
collective/z3cform/datagridfield_demo/browser/simple_templates/editform.pt
collective/z3cform/datagridfield_demo/browser/simple_templates/editform2.pt
collective/z3cform/datagridfield_demo/browser/simple_templates/editform3.pt
collective/z3cform/datagridfield_demo/browser/simple_templates/editform4.pt
collective/z3cform/datagridfield_demo/browser/simple_templates/editform5.pt
collective/z3cform/datagridfield_demo/browser/simple_templates/editform6.pt
collective/z3cform/datagridfield_demo/browser/simple_templates/editform7.pt
collective/z3cform/datagridfield_demo/browser/simple_templates/editform8.pt
docs/HISTORY.txt
docs/INSTALL.txt
docs/LICENSE.GPL
docs/LICENSE.txt