Metadata-Version: 1.1
Name: collective.z3cform.datagridfield-demo
Version: 0.6
Summary: Version of DataGridField for use with Dexterity / z3c.form - Demo views
Home-page: https://github.com/collective/collective.z3cform.datagridfield_demo
Author: Kevin Gill
Author-email: kevin@movieextras.ie
License: GPL
Keywords: Plone,Dexterity,z3c.form
Platform: UNKNOWN
Classifier: Framework :: Plone
Classifier: Programming Language :: Python
